<?xml version="1.0" encoding="UTF-8"?>
<!DOCTYPE mapper PUBLIC "-//mybatis.org//DTD Mapper 3.0//EN" "http://mybatis.org/dtd/mybatis-3-mapper.dtd">

<mapper namespace="com.pixcel.app.file.mapper.FileMapper">

    <!-- 파일 버전 조회 -->
    <select id="selectMaxVersion" resultType="int">
        SELECT NVL(MAX(file_version), 0)
		FROM attach_file
		WHERE project_id = #{projectId}
  			AND connect_address = #{connectAddress}
  			AND original_name = #{originalName}
    </select>

    <!-- 문서에 파일조회 -->
    <select id="selectAll" parameterType="String" resultType="FileVO">
        select
            file_id,
            project_id,
            version_id,
            file_code,
            original_name,
            stored_name,
            file_path,
            file_size,
            upload_user_id,
            upload_date,
            file_version,
            file_use_yn
        from attach_file
        where connect_address = #{connectAddress}
    </select>

    <!-- 파일 등록 -->
    <insert id="insertFile" parameterType="FileVO">
        <selectKey keyProperty="fileId"
           resultType="string"
           order="BEFORE">

    SELECT
        'ATTACH_FILE_'
        || TO_CHAR(SYSDATE, 'YYMM')
        || '_'
        || LPAD(
            NVL(
                MAX(TO_NUMBER(SUBSTR(file_id, -4))),
                0
            ) + 1,
            4,
            '0'
        )
    FROM attach_file
    WHERE file_id LIKE 'ATTACH_FILE_' || TO_CHAR(SYSDATE, 'YYMM') || '_%'

</selectKey>

        insert into attach_file (
            file_id,
            project_id,
            version_id,
            file_code,
            original_name,
            stored_name,
            file_path,
            file_size,
            upload_user_id,
            file_version,
            connect_address
        ) values (
            #{fileId},
            'PROJECT_ID_2606_0006',
            #{versionId},
            'f001',
            #{originalName},
            #{storedName},
            #{filePath},
            #{fileSize},
            #{uploadUserId},
            #{fileVersion},
            #{connectAddress}
        )
    </insert>

</mapper>